{"study":[{"xmlId":"4675","NOAAStudyId":"5211","studyName":"Waggoner - Whiskey Mountain - PSME - ITRDB WY028","doi":"https://doi.org/10.25921/bb04-6f55","uuid":"0847500a-ab54-44e4-b60f-d409ae95446c","dataPublisher":"NOAA","contactInfo":{"type":"CONTACT INFORMATION","shortName":"DOC/NOAA/NESDIS/NCEI","longName":"National Centers for Environmental Information, NESDIS, NOAA, U.S. Department of Commerce ","address":"325 Broadway, E/NE31","city":"Boulder","state":"CO","postalCode":"80305-3328","country":"USA","dataCenterUrl":"https://www.ncdc.noaa.gov/data-access/paleoclimatology-data","email":"paleo@noaa.gov","phone":"303-497-6280","fax":"303-497-6513","constraints":"Please cite original publication, online resource, dataset and publication DOIs (where available), and date accessed when using downloaded data. If there is no publication information, please cite investigator, title, online resource, and date accessed. The appearance of external links associated with a dataset does not constitute endorsement by the Department of Commerce/National Oceanic and Atmospheric Administration of external Web sites or the information, products or services contained therein. For other than authorized activities, the Department of Commerce/NOAA does not exercise any editorial control over the information you may find at these locations. These links are provided consistent with the stated purpose of this Department of Commerce/NOAA Web site."},"dataType":"TREE RING","investigators":"Waggoner, L.; Hill, S.","version":"1.0","funding":[],"studyNotes":"NOAA Template Chronology file added 2018-12-20. NOAA Template Raw Measurements file added 2019-02-08.","onlineResourceLink":"https://www.ncdc.noaa.gov/paleo/study/5211","difMetadataLink":"http://www1.ncdc.noaa.gov/pub/data/metadata/published/paleo/dif/xml/noaa-tree-5211.xml","isoMetadataLink":"http://www1.ncdc.noaa.gov/pub/data/metadata/published/paleo/iso/xml/noaa-tree-5211.xml","originalSource":null,"dataTypeInformation":"https://www.ncdc.noaa.gov/data-access/paleoclimatology-data/datasets/tree-ring","studyCode":"WY028","scienceKeywords":["Douglas-fir","Pseudotsuga menziesii (Mirb.) Franco","PSME"],"reconstruction":"N","contributionDate":"2002-12-09","entryId":"noaa-tree-5211","earliestYearBP":491,"mostRecentYearBP":-50,"earliestYearCE":1459,"mostRecentYearCE":2000,"publication":[],"site":[{"NOAASiteId":"17533","siteName":"Whiskey Mountain","siteCode":null,"mappable":"Y","locationName":"Continent>North America>United States Of America>Wyoming","geo":{"geoType":"Feature","geometry":{"type":"POINT","coordinates":["43.43","-109.55"]},"properties":{"southernmostLatitude":"43.43","northernmostLatitude":"43.43","westernmostLongitude":"-109.55","easternmostLongitude":"-109.55","minElevationMeters":"2696","maxElevationMeters":"2696"}},"paleoData":[{"dataTableName":"WY028","NOAADataTableId":"6937","earliestYear":1459,"mostRecentYear":2000,"timeUnit":"AD","earliestYearBP":491,"mostRecentYearBP":-50,"earliestYearCE":1459,"mostRecentYearCE":2000,"coreLengthMeters":null,"dataTableNotes":null,"species":[{"speciesCode":"PSME","scientificName":"Pseudotsuga menziesii (Mirb.) Franco","commonName":["Douglas-fir"]}],"dataFile":[{"fileUrl":"https://www.ncei.noaa.gov/pub/data/paleo/treering/measurements/correlation-stats/wy028.txt","urlDescription":"Correlation Stats","linkText":"wy028.txt","variables":[],"NOAAKeywords":["earth science>paleoclimate>tree-ring>width>more info"]},{"fileUrl":"https://www.ncei.noaa.gov/pub/data/paleo/treering/measurements/northamerica/usa/wy028.rwl","urlDescription":"Raw Measurements","linkText":"wy028.rwl","variables":[{"cvDataType":"TREE RING","cvWhat":"age variable>age","cvMaterial":null,"cvError":null,"cvUnit":"time unit>age unit>year Common Era","cvSeasonality":null,"cvDetail":null,"cvMethod":null,"cvAdditionalInfo":null,"cvFormat":"Numeric","cvShortName":null},{"cvDataType":"TREE RING","cvWhat":"physical property>thickness>total ring width","cvMaterial":null,"cvError":null,"cvUnit":"length unit>millimeter","cvSeasonality":null,"cvDetail":null,"cvMethod":null,"cvAdditionalInfo":"units are 0.01 mm if end-of-series marker is 999 and 0.001 mm if end-of-series marker is -9999","cvFormat":"Numeric","cvShortName":null}],"NOAAKeywords":["earth science>paleoclimate>tree-ring>width>ring width"]},{"fileUrl":"https://www.ncei.noaa.gov/pub/data/paleo/treering/measurements/northamerica/usa/wy028-noaa.rwl","urlDescription":"Raw Measurements - NOAA Template File","linkText":"wy028-noaa.rwl","variables":[{"cvDataType":"TREE RING","cvWhat":"age variable>age","cvMaterial":null,"cvError":null,"cvUnit":"time unit>age unit>year Common Era","cvSeasonality":null,"cvDetail":null,"cvMethod":null,"cvAdditionalInfo":null,"cvFormat":"Numeric","cvShortName":"age_CE"},{"cvDataType":"TREE RING","cvWhat":"physical property>thickness>total ring width","cvMaterial":null,"cvError":null,"cvUnit":"length unit>millimeter","cvSeasonality":null,"cvDetail":null,"cvMethod":null,"cvAdditionalInfo":"Tree ID: WSK103; units are 0.01 mm if end-of-series marker is 999 and 0.001 mm if end-of-series marker is -9999","cvFormat":"Numeric","cvShortName":"WSK103_raw"},{"cvDataType":"TREE RING","cvWhat":"physical property>thickness>total ring width","cvMaterial":null,"cvError":null,"cvUnit":"length unit>millimeter","cvSeasonality":null,"cvDetail":null,"cvMethod":null,"cvAdditionalInfo":"Tree ID: WSK105; units are 0.01 mm if end-of-series marker is 999 and 0.001 mm if end-of-series marker is -9999","cvFormat":"Numeric","cvShortName":"WSK105_raw"},{"cvDataType":"TREE RING","cvWhat":"physical property>thickness>total ring width","cvMaterial":null,"cvError":null,"cvUnit":"length unit>millimeter","cvSeasonality":null,"cvDetail":null,"cvMethod":null,"cvAdditionalInfo":"Tree ID: WSK005; units are 0.01 mm if end-of-series marker is 999 and 0.001 mm if end-of-series marker is -9999","cvFormat":"Numeric","cvShortName":"WSK005_raw"},{"cvDataType":"TREE RING","cvWhat":"physical property>thickness>total ring width","cvMaterial":null,"cvError":null,"cvUnit":"length unit>millimeter","cvSeasonality":null,"cvDetail":null,"cvMethod":null,"cvAdditionalInfo":"Tree ID: WSK104B; units are 0.01 mm if end-of-series marker is 999 and 0.001 mm if end-of-series marker is -9999","cvFormat":"Numeric","cvShortName":"WSK104B_raw"},{"cvDataType":"TREE RING","cvWhat":"physical property>thickness>total ring width","cvMaterial":null,"cvError":null,"cvUnit":"length unit>millimeter","cvSeasonality":null,"cvDetail":null,"cvMethod":null,"cvAdditionalInfo":"Tree ID: WSK010A; units are 0.01 mm if end-of-series marker is 999 and 0.001 mm if end-of-series marker is -9999","cvFormat":"Numeric","cvShortName":"WSK010A_raw"},{"cvDataType":"TREE RING","cvWhat":"physical property>thickness>total ring width","cvMaterial":null,"cvError":null,"cvUnit":"length unit>millimeter","cvSeasonality":null,"cvDetail":null,"cvMethod":null,"cvAdditionalInfo":"Tree ID: WSK052; units are 0.01 mm if end-of-series marker is 999 and 0.001 mm if end-of-series marker is -9999","cvFormat":"Numeric","cvShortName":"WSK052_raw"},{"cvDataType":"TREE RING","cvWhat":"physical property>thickness>total ring width","cvMaterial":null,"cvError":null,"cvUnit":"length unit>millimeter","cvSeasonality":null,"cvDetail":null,"cvMethod":null,"cvAdditionalInfo":"Tree ID: WSK008A; units are 0.01 mm if end-of-series marker is 999 and 0.001 mm if end-of-series marker is -9999","cvFormat":"Numeric","cvShortName":"WSK008A_raw"},{"cvDataType":"TREE RING","cvWhat":"physical property>thickness>total ring width","cvMaterial":null,"cvError":null,"cvUnit":"length unit>millimeter","cvSeasonality":null,"cvDetail":null,"cvMethod":null,"cvAdditionalInfo":"Tree ID: WSK010B; units are 0.01 mm if end-of-series marker is 999 and 0.001 mm if end-of-series marker is -9999","cvFormat":"Numeric","cvShortName":"WSK010B_raw"},{"cvDataType":"TREE RING","cvWhat":"physical property>thickness>total ring width","cvMaterial":null,"cvError":null,"cvUnit":"length unit>millimeter","cvSeasonality":null,"cvDetail":null,"cvMethod":null,"cvAdditionalInfo":"Tree ID: WSK054A; units are 0.01 mm if end-of-series marker is 999 and 0.001 mm if end-of-series marker is -9999","cvFormat":"Numeric","cvShortName":"WSK054A_raw"},{"cvDataType":"TREE RING","cvWhat":"physical property>thickness>total ring width","cvMaterial":null,"cvError":null,"cvUnit":"length unit>millimeter","cvSeasonality":null,"cvDetail":null,"cvMethod":null,"cvAdditionalInfo":"Tree ID: WSK106; units are 0.01 mm if end-of-series marker is 999 and 0.001 mm if end-of-series marker is -9999","cvFormat":"Numeric","cvShortName":"WSK106_raw"},{"cvDataType":"TREE RING","cvWhat":"physical property>thickness>total ring width","cvMaterial":null,"cvError":null,"cvUnit":"length unit>millimeter","cvSeasonality":null,"cvDetail":null,"cvMethod":null,"cvAdditionalInfo":"Tree ID: WSK012; units are 0.01 mm if end-of-series marker is 999 and 0.001 mm if end-of-series marker is -9999","cvFormat":"Numeric","cvShortName":"WSK012_raw"},{"cvDataType":"TREE RING","cvWhat":"physical property>thickness>total ring width","cvMaterial":null,"cvError":null,"cvUnit":"length unit>millimeter","cvSeasonality":null,"cvDetail":null,"cvMethod":null,"cvAdditionalInfo":"Tree ID: WSK051A; units are 0.01 mm if end-of-series marker is 999 and 0.001 mm if end-of-series marker is -9999","cvFormat":"Numeric","cvShortName":"WSK051A_raw"},{"cvDataType":"TREE RING","cvWhat":"physical property>thickness>total ring width","cvMaterial":null,"cvError":null,"cvUnit":"length unit>millimeter","cvSeasonality":null,"cvDetail":null,"cvMethod":null,"cvAdditionalInfo":"Tree ID: WSK150; units are 0.01 mm if end-of-series marker is 999 and 0.001 mm if end-of-series marker is -9999","cvFormat":"Numeric","cvShortName":"WSK150_raw"},{"cvDataType":"TREE RING","cvWhat":"physical property>thickness>total ring width","cvMaterial":null,"cvError":null,"cvUnit":"length unit>millimeter","cvSeasonality":null,"cvDetail":null,"cvMethod":null,"cvAdditionalInfo":"Tree ID: WSK157; units are 0.01 mm if end-of-series marker is 999 and 0.001 mm if end-of-series marker is -9999","cvFormat":"Numeric","cvShortName":"WSK157_raw"},{"cvDataType":"TREE RING","cvWhat":"physical property>thickness>total ring width","cvMaterial":null,"cvError":null,"cvUnit":"length unit>millimeter","cvSeasonality":null,"cvDetail":null,"cvMethod":null,"cvAdditionalInfo":"Tree ID: WSK003A; units are 0.01 mm if end-of-series marker is 999 and 0.001 mm if end-of-series marker is -9999","cvFormat":"Numeric","cvShortName":"WSK003A_raw"},{"cvDataType":"TREE RING","cvWhat":"physical property>thickness>total ring width","cvMaterial":null,"cvError":null,"cvUnit":"length unit>millimeter","cvSeasonality":null,"cvDetail":null,"cvMethod":null,"cvAdditionalInfo":"Tree ID: WSK003B; units are 0.01 mm if end-of-series marker is 999 and 0.001 mm if end-of-series marker is -9999","cvFormat":"Numeric","cvShortName":"WSK003B_raw"},{"cvDataType":"TREE RING","cvWhat":"physical property>thickness>total ring width","cvMaterial":null,"cvError":null,"cvUnit":"length unit>millimeter","cvSeasonality":null,"cvDetail":null,"cvMethod":null,"cvAdditionalInfo":"Tree ID: WSK102; units are 0.01 mm if end-of-series marker is 999 and 0.001 mm if end-of-series marker is -9999","cvFormat":"Numeric","cvShortName":"WSK102_raw"},{"cvDataType":"TREE RING","cvWhat":"physical property>thickness>total ring width","cvMaterial":null,"cvError":null,"cvUnit":"length unit>millimeter","cvSeasonality":null,"cvDetail":null,"cvMethod":null,"cvAdditionalInfo":"Tree ID: WSK009B; units are 0.01 mm if end-of-series marker is 999 and 0.001 mm if end-of-series marker is -9999","cvFormat":"Numeric","cvShortName":"WSK009B_raw"},{"cvDataType":"TREE RING","cvWhat":"physical property>thickness>total ring width","cvMaterial":null,"cvError":null,"cvUnit":"length unit>millimeter","cvSeasonality":null,"cvDetail":null,"cvMethod":null,"cvAdditionalInfo":"Tree ID: WSK007B; units are 0.01 mm if end-of-series marker is 999 and 0.001 mm if end-of-series marker is -9999","cvFormat":"Numeric","cvShortName":"WSK007B_raw"},{"cvDataType":"TREE RING","cvWhat":"physical property>thickness>total ring width","cvMaterial":null,"cvError":null,"cvUnit":"length unit>millimeter","cvSeasonality":null,"cvDetail":null,"cvMethod":null,"cvAdditionalInfo":"Tree ID: WSK051B; units are 0.01 mm if end-of-series marker is 999 and 0.001 mm if end-of-series marker is -9999","cvFormat":"Numeric","cvShortName":"WSK051B_raw"},{"cvDataType":"TREE RING","cvWhat":"physical property>thickness>total ring width","cvMaterial":null,"cvError":null,"cvUnit":"length unit>millimeter","cvSeasonality":null,"cvDetail":null,"cvMethod":null,"cvAdditionalInfo":"Tree ID: WSK007A; units are 0.01 mm if end-of-series marker is 999 and 0.001 mm if end-of-series marker is -9999","cvFormat":"Numeric","cvShortName":"WSK007A_raw"},{"cvDataType":"TREE RING","cvWhat":"physical property>thickness>total ring width","cvMaterial":null,"cvError":null,"cvUnit":"length unit>millimeter","cvSeasonality":null,"cvDetail":null,"cvMethod":null,"cvAdditionalInfo":"Tree ID: WSK 055A; units are 0.01 mm if end-of-series marker is 999 and 0.001 mm if end-of-series marker is -9999","cvFormat":"Numeric","cvShortName":"WSK_055A_raw"},{"cvDataType":"TREE RING","cvWhat":"physical property>thickness>total ring width","cvMaterial":null,"cvError":null,"cvUnit":"length unit>millimeter","cvSeasonality":null,"cvDetail":null,"cvMethod":null,"cvAdditionalInfo":"Tree ID: WSK006; units are 0.01 mm if end-of-series marker is 999 and 0.001 mm if end-of-series marker is -9999","cvFormat":"Numeric","cvShortName":"WSK006_raw"},{"cvDataType":"TREE RING","cvWhat":"physical property>thickness>total ring width","cvMaterial":null,"cvError":null,"cvUnit":"length unit>millimeter","cvSeasonality":null,"cvDetail":null,"cvMethod":null,"cvAdditionalInfo":"Tree ID: WSK006b; units are 0.01 mm if end-of-series marker is 999 and 0.001 mm if end-of-series marker is -9999","cvFormat":"Numeric","cvShortName":"WSK006b_raw"},{"cvDataType":"TREE RING","cvWhat":"physical property>thickness>total ring width","cvMaterial":null,"cvError":null,"cvUnit":"length unit>millimeter","cvSeasonality":null,"cvDetail":null,"cvMethod":null,"cvAdditionalInfo":"Tree ID: WSK055; units are 0.01 mm if end-of-series marker is 999 and 0.001 mm if end-of-series marker is -9999","cvFormat":"Numeric","cvShortName":"WSK055_raw"},{"cvDataType":"TREE RING","cvWhat":"physical property>thickness>total ring width","cvMaterial":null,"cvError":null,"cvUnit":"length unit>millimeter","cvSeasonality":null,"cvDetail":null,"cvMethod":null,"cvAdditionalInfo":"Tree ID: WSK011; units are 0.01 mm if end-of-series marker is 999 and 0.001 mm if end-of-series marker is -9999","cvFormat":"Numeric","cvShortName":"WSK011_raw"},{"cvDataType":"TREE RING","cvWhat":"physical property>thickness>total ring width","cvMaterial":null,"cvError":null,"cvUnit":"length unit>millimeter","cvSeasonality":null,"cvDetail":null,"cvMethod":null,"cvAdditionalInfo":"Tree ID: WSK060; units are 0.01 mm if end-of-series marker is 999 and 0.001 mm if end-of-series marker is -9999","cvFormat":"Numeric","cvShortName":"WSK060_raw"},{"cvDataType":"TREE RING","cvWhat":"physical property>thickness>total ring width","cvMaterial":null,"cvError":null,"cvUnit":"length unit>millimeter","cvSeasonality":null,"cvDetail":null,"cvMethod":null,"cvAdditionalInfo":"Tree ID: WSK 54C; units are 0.01 mm if end-of-series marker is 999 and 0.001 mm if end-of-series marker is -9999","cvFormat":"Numeric","cvShortName":"WSK_54C_raw"},{"cvDataType":"TREE RING","cvWhat":"physical property>thickness>total ring width","cvMaterial":null,"cvError":null,"cvUnit":"length unit>millimeter","cvSeasonality":null,"cvDetail":null,"cvMethod":null,"cvAdditionalInfo":"Tree ID: WSK054B; units are 0.01 mm if end-of-series marker is 999 and 0.001 mm if end-of-series marker is -9999","cvFormat":"Numeric","cvShortName":"WSK054B_raw"},{"cvDataType":"TREE RING","cvWhat":"physical property>thickness>total ring width","cvMaterial":null,"cvError":null,"cvUnit":"length unit>millimeter","cvSeasonality":null,"cvDetail":null,"cvMethod":null,"cvAdditionalInfo":"Tree ID: WSK056A; units are 0.01 mm if end-of-series marker is 999 and 0.001 mm if end-of-series marker is -9999","cvFormat":"Numeric","cvShortName":"WSK056A_raw"},{"cvDataType":"TREE RING","cvWhat":"physical property>thickness>total ring width","cvMaterial":null,"cvError":null,"cvUnit":"length unit>millimeter","cvSeasonality":null,"cvDetail":null,"cvMethod":null,"cvAdditionalInfo":"Tree ID: WSK053; units are 0.01 mm if end-of-series marker is 999 and 0.001 mm if end-of-series marker is -9999","cvFormat":"Numeric","cvShortName":"WSK053_raw"},{"cvDataType":"TREE RING","cvWhat":"physical property>thickness>total ring width","cvMaterial":null,"cvError":null,"cvUnit":"length unit>millimeter","cvSeasonality":null,"cvDetail":null,"cvMethod":null,"cvAdditionalInfo":"Tree ID: WSK009; units are 0.01 mm if end-of-series marker is 999 and 0.001 mm if end-of-series marker is -9999","cvFormat":"Numeric","cvShortName":"WSK009_raw"},{"cvDataType":"TREE RING","cvWhat":"physical property>thickness>total ring width","cvMaterial":null,"cvError":null,"cvUnit":"length unit>millimeter","cvSeasonality":null,"cvDetail":null,"cvMethod":null,"cvAdditionalInfo":"Tree ID: WSK057; units are 0.01 mm if end-of-series marker is 999 and 0.001 mm if end-of-series marker is -9999","cvFormat":"Numeric","cvShortName":"WSK057_raw"},{"cvDataType":"TREE RING","cvWhat":"physical property>thickness>total ring width","cvMaterial":null,"cvError":null,"cvUnit":"length unit>millimeter","cvSeasonality":null,"cvDetail":null,"cvMethod":null,"cvAdditionalInfo":"Tree ID: WSK001A; units are 0.01 mm if end-of-series marker is 999 and 0.001 mm if end-of-series marker is -9999","cvFormat":"Numeric","cvShortName":"WSK001A_raw"}],"NOAAKeywords":["earth science>paleoclimate>tree-ring>width>more info"]},{"fileUrl":"https://www.ncei.noaa.gov/pub/data/paleo/treering/chronologies/northamerica/usa/wy028.crn","urlDescription":"Chronology","linkText":"wy028.crn","variables":[{"cvDataType":"TREE RING","cvWhat":"age variable>age","cvMaterial":null,"cvError":null,"cvUnit":"time unit>age unit>year Common Era","cvSeasonality":null,"cvDetail":null,"cvMethod":null,"cvAdditionalInfo":null,"cvFormat":"Numeric","cvShortName":null},{"cvDataType":"TREE RING","cvWhat":"sampling metadata>number of samples","cvMaterial":null,"cvError":null,"cvUnit":"dimensionless>count","cvSeasonality":null,"cvDetail":null,"cvMethod":null,"cvAdditionalInfo":null,"cvFormat":"Numeric","cvShortName":null},{"cvDataType":"TREE RING","cvWhat":"statistical variable>proxy composite>tree ring standardized growth index","cvMaterial":null,"cvError":null,"cvUnit":null,"cvSeasonality":null,"cvDetail":"composited","cvMethod":"computational method>tree ring chronology method>standard chronology method","cvAdditionalInfo":null,"cvFormat":"Numeric","cvShortName":null}],"NOAAKeywords":["earth science>paleoclimate>tree-ring>width>ring width"]},{"fileUrl":"https://www.ncei.noaa.gov/pub/data/paleo/treering/chronologies/northamerica/usa/wy028r.crn","urlDescription":"Chronology","linkText":"wy028r.crn","variables":[{"cvDataType":"TREE RING","cvWhat":"age variable>age","cvMaterial":null,"cvError":null,"cvUnit":"time unit>age unit>year Common Era","cvSeasonality":null,"cvDetail":null,"cvMethod":null,"cvAdditionalInfo":null,"cvFormat":"Numeric","cvShortName":null},{"cvDataType":"TREE RING","cvWhat":"sampling metadata>number of samples","cvMaterial":null,"cvError":null,"cvUnit":"dimensionless>count","cvSeasonality":null,"cvDetail":null,"cvMethod":null,"cvAdditionalInfo":null,"cvFormat":"Numeric","cvShortName":null},{"cvDataType":"TREE RING","cvWhat":"statistical variable>proxy composite>tree ring standardized growth index","cvMaterial":null,"cvError":null,"cvUnit":null,"cvSeasonality":null,"cvDetail":"composited","cvMethod":"computational method>tree ring chronology method>residual chronology method","cvAdditionalInfo":null,"cvFormat":"Numeric","cvShortName":null}],"NOAAKeywords":["earth science>paleoclimate>tree-ring>width>ring width"]},{"fileUrl":"https://www.ncei.noaa.gov/pub/data/paleo/treering/chronologies/northamerica/usa/wy028-noaa.crn","urlDescription":"Chronology - NOAA Template File","linkText":"wy028-noaa.crn","variables":[{"cvDataType":"TREE RING","cvWhat":"age variable>age","cvMaterial":null,"cvError":null,"cvUnit":"time unit>age unit>year Common Era","cvSeasonality":null,"cvDetail":null,"cvMethod":null,"cvAdditionalInfo":null,"cvFormat":"Numeric","cvShortName":null},{"cvDataType":"TREE RING","cvWhat":"sampling metadata>number of samples","cvMaterial":null,"cvError":null,"cvUnit":"dimensionless>count","cvSeasonality":null,"cvDetail":null,"cvMethod":null,"cvAdditionalInfo":null,"cvFormat":"Numeric","cvShortName":null},{"cvDataType":"TREE RING","cvWhat":"statistical variable>proxy composite>tree ring standardized growth index","cvMaterial":null,"cvError":null,"cvUnit":null,"cvSeasonality":null,"cvDetail":"composited","cvMethod":"computational method>tree ring chronology method>standard chronology method","cvAdditionalInfo":null,"cvFormat":"Numeric","cvShortName":null}],"NOAAKeywords":["earth science>paleoclimate>tree-ring>width>ring width"]},{"fileUrl":"https://www.ncei.noaa.gov/pub/data/paleo/treering/chronologies/northamerica/usa/wy028r-noaa.crn","urlDescription":"Chronology - NOAA Template File","linkText":"wy028r-noaa.crn","variables":[{"cvDataType":"TREE RING","cvWhat":"age variable>age","cvMaterial":null,"cvError":null,"cvUnit":"time unit>age unit>year Common Era","cvSeasonality":null,"cvDetail":null,"cvMethod":null,"cvAdditionalInfo":null,"cvFormat":"Numeric","cvShortName":null},{"cvDataType":"TREE RING","cvWhat":"sampling metadata>number of samples","cvMaterial":null,"cvError":null,"cvUnit":"dimensionless>count","cvSeasonality":null,"cvDetail":null,"cvMethod":null,"cvAdditionalInfo":null,"cvFormat":"Numeric","cvShortName":null},{"cvDataType":"TREE RING","cvWhat":"statistical variable>proxy composite>tree ring standardized growth index","cvMaterial":null,"cvError":null,"cvUnit":null,"cvSeasonality":null,"cvDetail":"composited","cvMethod":"computational method>tree ring chronology method>residual chronology method","cvAdditionalInfo":null,"cvFormat":"Numeric","cvShortName":null}],"NOAAKeywords":["earth science>paleoclimate>tree-ring>width>ring width"]}]}]}]}]}